ogpu/__init__.py
ogpu/agent/__init__.py
ogpu/agent/terminal.py
ogpu/client/__init__.py
ogpu/client/chain_config.py
ogpu/client/config.py
ogpu/client/contracts.py
ogpu/client/environment.py
ogpu/client/nonce_manager.py
ogpu/client/nonce_utils.py
ogpu/client/responses.py
ogpu/client/source.py
ogpu/client/task.py
ogpu/client/types.py
ogpu/client/utils.py
ogpu/client/web3_manager.py
ogpu/client/abis/mainnet/ControllerAbi.json
ogpu/client/abis/mainnet/ManagerAbi.json
ogpu/client/abis/mainnet/NexusAbi.json
ogpu/client/abis/mainnet/ResponseAbi.json
ogpu/client/abis/mainnet/SourceAbi.json
ogpu/client/abis/mainnet/TaskAbi.json
ogpu/client/abis/mainnet/TerminalAbi.json
ogpu/client/abis/mainnet/VaultAbi.json
ogpu/client/abis/testnet/ControllerAbi.json
ogpu/client/abis/testnet/ManagerAbi.json
ogpu/client/abis/testnet/NexusAbi.json
ogpu/client/abis/testnet/ResponseAbi.json
ogpu/client/abis/testnet/SourceAbi.json
ogpu/client/abis/testnet/TaskAbi.json
ogpu/client/abis/testnet/TerminalAbi.json
ogpu/client/abis/testnet/VaultAbi.json
ogpu/service/__init__.py
ogpu/service/config.py
ogpu/service/decorators.py
ogpu/service/handler.py
ogpu/service/logger.py
ogpu/service/server.py
ogpu-0.2.0.14.dist-info/METADATA
ogpu-0.2.0.14.dist-info/WHEEL
ogpu-0.2.0.14.dist-info/top_level.txt
ogpu-0.2.0.14.dist-info/RECORD
