Metadata-Version: 2.4
Name: ogpu
Version: 0.2.0.14
Summary: OpenGPU SDK for distributed AI task deployment
Author-email: Kutay <kutay@opengpu.network>
License: MIT
Classifier: Programming Language :: Python :: 3
Classifier: License :: OSI Approved :: MIT License
Classifier: Operating System :: OS Independent
Requires-Python: >=3.8
Requires-Dist: colorama==0.4.6
Requires-Dist: fastapi==0.115.12
Requires-Dist: pydantic==2.11.4
Requires-Dist: uvicorn==0.34.2
Requires-Dist: sentry_sdk==2.29.1
Requires-Dist: python-dotenv==1.1.0
Requires-Dist: web3==7.12.0
Requires-Dist: requests==2.32.3
